stitching/__init__.py
stitching/blender.py
stitching/camera_adjuster.py
stitching/camera_estimator.py
stitching/camera_wave_corrector.py
stitching/cropper.py
stitching/exposure_error_compensator.py
stitching/feature_detector.py
stitching/feature_matcher.py
stitching/images.py
stitching/megapix_scaler.py
stitching/seam_finder.py
stitching/stitcher.py
stitching/stitching_error.py
stitching/subsetter.py
stitching/timelapser.py
stitching/verbose.py
stitching/warper.py
stitching/cli/__init__.py
stitching/cli/stitch.py
stitching_headless-0.6.1.dist-info/licenses/LICENSE
stitching_headless-0.6.1.dist-info/METADATA
stitching_headless-0.6.1.dist-info/WHEEL
stitching_headless-0.6.1.dist-info/entry_points.txt
stitching_headless-0.6.1.dist-info/top_level.txt
stitching_headless-0.6.1.dist-info/RECORD
