Metadata-Version: 2.4
Name: stitching-headless
Version: 0.6.1
Summary: A Python package for fast and robust Image Stitching
Author: Lukas Weber
Author-email: l.a.weber@outlook.de
License: Apache License 2.0
Project-URL: Source, https://github.com/lukasalexanderweber/stitching
Project-URL: Bug Tracker, https://github.com/lukasalexanderweber/stitching/issues
Platform: any
Classifier: Programming Language :: Python :: 3 :: Only
License-File: LICENSE
Requires-Dist: opencv-python-headless>=4.0.1
Requires-Dist: largestinteriorrectangle
Dynamic: license-file
